[
    {
        "inputs": [],
        "stateMutability": "nonpayable",
        "type": "constructor"
    },
    {
        "anonymous": false,
        "inputs": [
            {
                "indexed": false,
                "internalType": "uint256",
                "name": "expenseId",
                "type": "uint256"
            },
            {
                "indexed": false,
                "internalType": "string",
                "name": "description",
                "type": "string"
            },
            {
                "indexed": false,
                "internalType": "uint256",
                "name": "amount",
                "type": "uint256"
            },
            {
                "indexed": false,
                "internalType": "string",
                "name": "date",
                "type": "string"
            }
        ],
        "name": "ExpenseCreate",
        "type": "event"
    },
    {
        "anonymous": false,
        "inputs": [
            {
                "indexed": false,
                "internalType": "uint256",
                "name": "expenseId",
                "type": "uint256"
            }
        ],
        "name": "ExpenseDelete",
        "type": "event"
    },
    {
        "anonymous": false,
        "inputs": [
            {
                "indexed": false,
                "internalType": "uint256",
                "name": "expenseId",
                "type": "uint256"
            },
            {
                "indexed": false,
                "internalType": "string",
                "name": "description",
                "type": "string"
            },
            {
                "indexed": false,
                "internalType": "uint256",
                "name": "amount",
                "type": "uint256"
            },
            {
                "indexed": false,
                "internalType": "string",
                "name": "date",
                "type": "string"
            }
        ],
        "name": "ExpenseUpdate",
        "type": "event"
    },
    {
        "inputs": [
            {
                "internalType": "string",
                "name": "_description",
                "type": "string"
            },
            {
                "internalType": "uint256",
                "name": "_amount",
                "type": "uint256"
            },
            {
                "internalType": "string",
                "name": "_date",
                "type": "string"
            }
        ],
        "name": "createExpense",
        "outputs": [],
        "stateMutability": "nonpayable",
        "type": "function"
    },
    {
        "inputs": [
            {
                "internalType": "uint256",
                "name": "_expenseId",
                "type": "uint256"
            }
        ],
        "name": "deleteExpense",
        "outputs": [],
        "stateMutability": "nonpayable",
        "type": "function"
    },
    {
        "inputs": [],
        "name": "getAllExpenses",
        "outputs": [
            {
                "components": [
                    {
                        "internalType": "uint256",
                        "name": "id",
                        "type": "uint256"
                    },
                    {
                        "internalType": "string",
                        "name": "description",
                        "type": "string"
                    },
                    {
                        "internalType": "uint256",
                        "name": "amount",
                        "type": "uint256"
                    },
                    {
                        "internalType": "string",
                        "name": "date",
                        "type": "string"
                    }
                ],
                "internalType": "struct ExpenseTracker.Expense[]",
                "name": "",
                "type": "tuple[]"
            }
        ],
        "stateMutability": "view",
        "type": "function"
    },
    {
        "inputs": [
            {
                "internalType": "uint256",
                "name": "_expenseId",
                "type": "uint256"
            }
        ],
        "name": "getExpenseById",
        "outputs": [
            {
                "components": [
                    {
                        "internalType": "uint256",
                        "name": "id",
                        "type": "uint256"
                    },
                    {
                        "internalType": "string",
                        "name": "description",
                        "type": "string"
                    },
                    {
                        "internalType": "uint256",
                        "name": "amount",
                        "type": "uint256"
                    },
                    {
                        "internalType": "string",
                        "name": "date",
                        "type": "string"
                    }
                ],
                "internalType": "struct ExpenseTracker.Expense",
                "name": "",
                "type": "tuple"
            }
        ],
        "stateMutability": "view",
        "type": "function"
    },
    {
        "inputs": [
            {
                "internalType": "uint256",
                "name": "_expenseId",
                "type": "uint256"
            },
            {
                "internalType": "string",
                "name": "_description",
                "type": "string"
            },
            {
                "internalType": "uint256",
                "name": "_amount",
                "type": "uint256"
            },
            {
                "internalType": "string",
                "name": "_date",
                "type": "string"
            }
        ],
        "name": "updateExpense",
        "outputs": [],
        "stateMutability": "nonpayable",
        "type": "function"
    },
    {
        "inputs": [
            {
                "internalType": "uint256",
                "name": "_expenseId",
                "type": "uint256"
            }
        ],
        "name": "viewExpense",
        "outputs": [
            {
                "components": [
                    {
                        "internalType": "uint256",
                        "name": "id",
                        "type": "uint256"
                    },
                    {
                        "internalType": "string",
                        "name": "description",
                        "type": "string"
                    },
                    {
                        "internalType": "uint256",
                        "name": "amount",
                        "type": "uint256"
                    },
                    {
                        "internalType": "string",
                        "name": "date",
                        "type": "string"
                    }
                ],
                "internalType": "struct ExpenseTracker.Expense",
                "name": "",
                "type": "tuple"
            }
        ],
        "stateMutability": "view",
        "type": "function"
    }
]
